{
  "IsRegenerate": false,
  "MenuPosition": "main",
  "RelativeNamespace": "Job",
  "EntityName": "Employee",
  "EntityNamePlural": "Employee",
  "TableName": "tbl_Employee",
  "PrimaryKeyType": "Guid",
  "BaseClass": "Entity",
  "EntityHistory": false,
  "AutoMigration": false,
  "UpdateDatabase": false,
  "CreateUserInterface": true,
  "CreateViewOnly": true,
  "CreateExcelExport": true,
  "IsNonModalCRUDPage": false,
  "IsMasterDetailPage": false,
  "GenerateOverridableEntity": false,
  "GenerateUnitTest": false,
  "GenerateUiTest": false,
  "PagePermission": {
    "Host": true,
    "Tenant": true
  },
  "Properties": [
    {
      "Name": "Name",
      "Type": "string",
      "MaxLength": -1,
      "MinLength": -1,
      "Range": {
        "IsRangeSet": false,
        "MinimumValue": 0.0,
        "MaximumValue": 0.0
      },
      "Required": false,
      "Nullable": false,
      "Regex": "",
      "UserInterface": {
        "AdvancedFilter": false,
        "List": true,
        "CreateOrUpdate": true
      },
      "ViewType": null,
      "AdditionalData": {}
    },
    {
      "Name": "PhoneNo",
      "Type": "string",
      "MaxLength": -1,
      "MinLength": -1,
      "Range": {
        "IsRangeSet": false,
        "MinimumValue": 0.0,
        "MaximumValue": 0.0
      },
      "Required": false,
      "Nullable": false,
      "Regex": "",
      "UserInterface": {
        "AdvancedFilter": false,
        "List": true,
        "CreateOrUpdate": true
      },
      "ViewType": null,
      "AdditionalData": {}
    },
    {
      "Name": "Gender",
      "Type": "GenderEnum",
      "MaxLength": 0,
      "MinLength": 0,
      "Range": {
        "IsRangeSet": false,
        "MinimumValue": 0.0,
        "MaximumValue": 0.0
      },
      "Required": false,
      "Nullable": false,
      "Regex": "",
      "UserInterface": {
        "AdvancedFilter": false,
        "List": true,
        "CreateOrUpdate": true
      },
      "ViewType": null,
      "AdditionalData": {}
    },
    {
      "Name": "Dbo",
      "Type": "DateTime",
      "MaxLength": 0,
      "MinLength": 0,
      "Range": {
        "IsRangeSet": false,
        "MinimumValue": 0.0,
        "MaximumValue": 0.0
      },
      "Required": false,
      "Nullable": false,
      "Regex": "",
      "UserInterface": {
        "AdvancedFilter": false,
        "List": true,
        "CreateOrUpdate": true
      },
      "ViewType": null,
      "AdditionalData": {}
    },
    {
      "Name": "Experience",
      "Type": "string",
      "MaxLength": -1,
      "MinLength": -1,
      "Range": {
        "IsRangeSet": false,
        "MinimumValue": 0.0,
        "MaximumValue": 0.0
      },
      "Required": false,
      "Nullable": false,
      "Regex": "",
      "UserInterface": {
        "AdvancedFilter": false,
        "List": false,
        "CreateOrUpdate": true
      },
      "ViewType": null,
      "AdditionalData": {}
    },
    {
      "Name": "Qualification",
      "Type": "string",
      "MaxLength": -1,
      "MinLength": -1,
      "Range": {
        "IsRangeSet": false,
        "MinimumValue": 0.0,
        "MaximumValue": 0.0
      },
      "Required": false,
      "Nullable": false,
      "Regex": "",
      "UserInterface": {
        "AdvancedFilter": false,
        "List": true,
        "CreateOrUpdate": true
      },
      "ViewType": null,
      "AdditionalData": {}
    },
    {
      "Name": "ExpectedSalary",
      "Type": "decimal",
      "MaxLength": 0,
      "MinLength": 0,
      "Range": {
        "IsRangeSet": false,
        "MinimumValue": 0.0,
        "MaximumValue": 0.0
      },
      "Required": false,
      "Nullable": false,
      "Regex": "",
      "UserInterface": {
        "AdvancedFilter": false,
        "List": true,
        "CreateOrUpdate": true
      },
      "ViewType": null,
      "AdditionalData": {}
    },
    {
      "Name": "CommitmentYear",
      "Type": "int",
      "MaxLength": 0,
      "MinLength": 0,
      "Range": {
        "IsRangeSet": false,
        "MinimumValue": 0.0,
        "MaximumValue": 0.0
      },
      "Required": false,
      "Nullable": false,
      "Regex": "",
      "UserInterface": {
        "AdvancedFilter": false,
        "List": false,
        "CreateOrUpdate": true
      },
      "ViewType": null,
      "AdditionalData": {}
    },
    {
      "Name": "Photo",
      "Type": "file",
      "MaxLength": 0,
      "MinLength": 0,
      "Range": {
        "IsRangeSet": false,
        "MinimumValue": 0.0,
        "MaximumValue": 0.0
      },
      "Required": false,
      "Nullable": true,
      "Regex": "",
      "UserInterface": {
        "AdvancedFilter": false,
        "List": false,
        "CreateOrUpdate": true
      },
      "ViewType": null,
      "AdditionalData": {}
    }
  ],
  "NavigationProperties": [
    {
      "Namespace": "Suktas.Payroll.Master",
      "ForeignEntityName": "JobSkill",
      "ForeignEntityNamePlural": "JobSkills",
      "IdType": "Guid",
      "IsNullable": false,
      "PropertyName": "JobSkillId",
      "DisplayPropertyName": "Name",
      "DuplicationNumber": 0,
      "RelationType": "single",
      "ViewType": "Dropdown"
    }
  ],
  "NavigationPropertyOneToManyTables": [],
  "EnumDefinitions": [
    {
      "Name": "GenderEnum",
      "Namespace": "Suktas.Payroll.Master",
      "EnumProperties": [
        {
          "Name": "Male",
          "Value": 1
        },
        {
          "Name": "Female",
          "Value": 2
        },
        {
          "Name": "Others",
          "Value": 3
        }
      ]
    }
  ],
  "DbContext": null
}